{
  "id": "EB02-061_p1",
  "name": "Monkey.D.Luffy",
  "cost": 6,
  "power": 7000,
  "color": "Purple",
  "cardType": "Character",
  "keywords": [],
  "effects": [
    {
      "trigger": "OnAttack",
      "condition": {
        "type": "Always"
      },
      "actions": [
        {
          "type": "TrashCard",
          "count": 2,
          "from": "OwnHand"
        },
        {
          "type": "Rest",
          "target": {
            "scope": "Self"
          }
        },
        {
          "type": "TakeLifeToHand",
          "count": 1
        }
      ]
    }
  ]
}