{
  "id": "EB03-046",
  "name": "Miss Doublefinger(Zala)",
  "cost": 4,
  "power": 5000,
  "color": "Black",
  "cardType": "Character",
  "keywords": [],
  "effects": [
    {
      "trigger": "OnPlay",
      "condition": {
        "type": "Always"
      },
      "actions": [
        {
          "type": "DrawCard",
          "count": 1
        }
      ]
    },
    {
      "trigger": "OnKO",
      "actions": [
        {
          "type": "TrashFromHand",
          "count": 2,
          "filter": {},
          "thenActions": []
        }
      ]
    }
  ],
  "counter": 1000
}
