{
  "id": "OP03-036",
  "effectText": "[Main] You may rest 1 of your {East Blue} type Characters: Set up to 1 of your [Kuro] cards as active.",
  "effects": [
    {
      "trigger": "Activated",
      "conditions": [],
      "actions": [
        {
          "type": "Rest",
          "target": {
            "scope": "ChooseOwnCharacter",
            "filter": {
              "type": "East Blue"
            },
            "maxCount": 1
          }
        },
        {
          "type": "Rest",
          "target": {
            "scope": "ChooseOwnCharacter",
            "filter": {
              "name": "Kuro"
            },
            "maxCount": 1
          }
        }
      ]
    }
  ]
}
