{
  "id": "OP09-010_r1",
  "name": "Bonk Punch",
  "cost": 4,
  "power": 5000,
  "color": "Red",
  "cardType": "Character",
  "keywords": [],
  "effects": [
    {
      "trigger": "OnPlay",
      "actions": [
        {
          "type": "PlayFromHand",
          "filter": {
            "subType": "Monster"
          }
        }
      ]
    },
    {
      "trigger": "OnAttack",
      "condition": {
        "type": "HasRestingDon",
        "count": 1
      },
      "actions": [
        {
          "type": "PowerBoost",
          "amount": 2000,
          "target": {
            "scope": "Self"
          },
          "duration": "EndOfTurn"
        }
      ]
    }
  ],
  "counter": 1000
}