{
  "id": "OP09-028",
  "name": "Sanji",
  "cost": 5,
  "power": 6000,
  "color": "Green",
  "cardType": "Character",
  "keywords": [],
  "effects": [
    {
      "trigger": "OnKO",
      "actions": [
        {
          "type": "TakeLifeToHand",
          "count": 1
        },
        {
          "type": "PlayFromHand",
          "filter": {
            "subType": "ODYSSEY",
            "maxCost": 4
          }
        },
        {
          "type": "PlayFromHand",
          "filter": {
            "subType": "Straw Hat Crew",
            "maxCost": 4
          }
        }
      ]
    }
  ],
  "counter": 1000
}