{
  "id": "OP13-086",
  "name": "Saint Shalria",
  "cost": 1,
  "power": 0,
  "color": "Black",
  "cardType": "Character",
  "keywords": [],
  "effects": [
    {
      "trigger": "OnPlay",
      "actions": [
        {
          "type": "SearchDeck",
          "filter": {
            "kind": "ByName",
            "name": "Celestial Dragons"
          },
          "destination": "hand"
        },
        {
          "type": "TrashFromHand",
          "count": 1,
          "filter": {},
          "thenActions": []
        }
      ]
    }
  ],
  "counter": 1000
}
