{
  "id": "OP13-004",
  "name": "Sabo",
  "cost": 0,
  "power": 5000,
  "color": "Multi",
  "cardType": "Leader",
  "keywords": [],
  "effects": [
    {
      "trigger": "Activated",
      "condition": {
        "type": "HasCardOnBoard",
        "name": "Character"
      },
      "actions": [
        {
          "type": "PowerBoost",
          "amount": 1000,
          "target": {
            "scope": "AllOwnCharactersAndLeader"
          },
          "duration": "EndOfTurn"
        }
      ]
    }
  ]
}