{
  "id": "OP14-037",
  "name": "For Fun",
  "cost": 1,
  "power": 0,
  "color": "Green",
  "cardType": "Event",
  "keywords": [],
  "effects": [
    {
      "trigger": "Activated",
      "condition": {
        "type": "HasRestingDon",
        "count": 3
      },
      "actions": [
        {
          "type": "KO",
          "target": {
            "scope": "ChooseOpponentCharacter",
            "maxPower": 7000
          }
        }
      ]
    },
    {
      "trigger": "Counter",
      "actions": [
        {
          "type": "PowerBoost",
          "amount": 3000,
          "target": {
            "scope": "OwnLeader"
          },
          "duration": "EndOfBattle"
        }
      ]
    }
  ]
}