{
  "id": "OP14-069_p1",
  "name": "Donquixote Doflamingo",
  "cost": 10,
  "power": 10000,
  "color": "Purple",
  "cardType": "Character",
  "keywords": [],
  "effects": [
    {
      "trigger": "Activated",
      "condition": {
        "type": "HasCardOnBoard",
        "name": "Donquixote Pirates"
      },
      "actions": [
        {
          "type": "KO",
          "target": {
            "scope": "ChooseOpponentCharacter",
            "maxCost": 8
          }
        }
      ]
    },
    {
      "trigger": "Activated",
      "actions": [
        {
          "type": "Rest",
          "target": {
            "scope": "ChooseOpponentCharacter",
            "maxCost": 7
          }
        },
        {
          "type": "Rest",
          "target": {
            "scope": "ChooseOpponentCharacter",
            "maxCost": 7
          }
        },
        {
          "type": "Rest",
          "target": {
            "scope": "ChooseOpponentCharacter",
            "maxCost": 7
          }
        }
      ]
    }
  ]
}