{
  "0": {
    "trigger": "OnPlay",
    "condition": {
      "type": "LeaderIsName",
      "name": "Rebecca"
    },
    "actions": [
      {
        "type": "TrashFromHand",
        "optional": true,
        "filter": {
          "excludeSelf": true
        },
        "count": 1
      },
      {
        "type": "GiveKeyword",
        "keyword": "Rush",
        "target": {
          "scope": "Self"
        },
        "duration": "DuringYourTurn"
      }
    ]
  },
  "1": {
    "trigger": "OnKO",
    "actions": [
      {
        "type": "ReturnToHand",
        "target": {
          "scope": "Self"
        }
      }
    ]
  },
  "id": "OP15-042"
}
