{
  "id": "ST10-014",
  "name": "Wire",
  "cost": 3,
  "power": 3000,
  "color": "Purple",
  "cardType": "Character",
  "keywords": [
    "Blocker"
  ],
  "effects": [
    {
      "trigger": "OnBlock",
      "actions": [
        {
          "type": "Rest",
          "target": {
            "scope": "Self"
          }
        }
      ]
    },
    {
      "trigger": "Activated",
      "actions": [
        {
          "type": "Draw",
          "count": 1
        },
        {
          "type": "TrashCard",
          "count": 1,
          "from": "OwnHand"
        }
      ]
    }
  ],
  "counter": 1000
}