{
  "id": "ST12-002",
  "name": "Kuina",
  "cost": 3,
  "power": 2000,
  "color": "Green",
  "cardType": "Character",
  "keywords": [],
  "effects": [
    {
      "trigger": "Activated",
      "actions": [
        {
          "type": "Rest",
          "target": {
            "scope": "Self"
          }
        },
        {
          "type": "Rest",
          "target": {
            "scope": "ChooseOpponentCharacter",
            "maxCost": 4
          }
        }
      ]
    },
    {
      "trigger": "Trigger",
      "actions": [
        {
          "type": "PlaySelf"
        }
      ]
    }
  ],
  "counter": 1000
}