{
  "id": "ST18-002_p1",
  "name": "O-Nami",
  "cost": 4,
  "power": 2000,
  "color": "Purple",
  "cardType": "Character",
  "keywords": [
    "Blocker"
  ],
  "effects": [
    {
      "trigger": "OnPlay",
      "condition": {
        "type": "HasRestingDon",
        "count": 8
      },
      "actions": [
        {
          "type": "TrashFromHand",
          "count": 1,
          "filter": {},
          "thenActions": []
        },
        {
          "type": "DrawCard",
          "count": 2
        }
      ]
    }
  ],
  "counter": 1000
}
