{
  "id": "ST22-011",
  "name": "Whitey Bay",
  "cost": 1,
  "power": 1000,
  "color": "Blue",
  "cardType": "Character",
  "keywords": [],
  "effects": [
    {
      "trigger": "OnPlay",
      "condition": {
        "type": "Always"
      },
      "actions": [
        {
          "type": "RevealFromHand",
          "count": 2,
          "filter": { "subType": "Whitebeard Pirates" },
          "thenActions": [
            {
              "type": "PowerBoost",
              "amount": 2000,
              "target": {
                "scope": "OwnLeader"
              },
              "duration": "EndOfTurn"
            }
          ]
        }
      ]
    }
  ],
  "counter": 2000
}
