{
  "id": "ST29-014",
  "effects": [
    {
      "trigger": "Activated",
      "condition": {
        "type": "Always"
      },
      "actions": [
        {
          "type": "TrashFromHand",
          "filter": {
            "subType": "Trigger"
          },
          "thenActions": [
            {
              "type": "DrawCard",
              "count": 1
            },
            {
              "type": "AttachDon",
              "count": 1,
              "target": {
                "scope": "ChooseOwnCharacterOrLeader"
              },
              "filter": {
                "status": "Rested"
              }
            }
          ]
        }
      ]
    }
  ]
}
