{
  "id": "OP10-024",
  "name": "Edward.Newgate",
  "set": "OP-10",
  "verdict": "major",
  "issues": [
    {
      "severity": "major",
      "field": "effects[0].condition",
      "description": "Condition missing: 'If you have 2 or more rested Characters' requires HasRestingDon condition with value 2 or similar. Current condition is 'Always', which doesn't check for rested character requirement."
    },
    {
      "severity": "major",
      "field": "effects[0].actions[1].target",
      "description": "Second action (KO) has incorrect target scope. Text specifies 'rested Characters with a cost of 3 or less' but target only filters by maxCost, missing the 'rested' status requirement."
    }
  ],
  "suggestedDsl": {
    "trigger": "OnPlay",
    "condition": {
      "type": "HasRestingDon",
      "value": 2
    },
    "actions": [
      {
        "type": "Rest",
        "target": {
          "scope": "ChooseOpponentCharacter",
          "maxCost": 5,
          "maxTargets": 1
        }
      },
      {
        "type": "KO",
        "target": {
          "scope": "ChooseOpponentCharacter",
          "maxCost": 3,
          "resting": true,
          "maxTargets": 1
        }
      }
    ]
  },
  "auditedAt": "2026-05-05T11:32:42.261Z"
}
